{
  "meta": {
    "device": "Sensor",
    "manufacturer": "Penteon",
    "make": "Env100 Series",
    "model": "env100-v1.0",
    "sku": "Env100-Mar2024",
    "type": "Indoor Environmental Air Quality Sensor",
    "communicationProtocol": "Modbus"
  },

  "registers": [
    {
      "name": "Temperature",
      "dataKey": "value2",
      "addressType": "Coil",
      "address": "1101",
      "minValue": -8000,
      "maxValue": 8000,
      "default_value": 0,
      "units": "°C",
      "dataType": "Word",
      "multiplier": 0.01,
      "rw": "r"
    },
    {
      "name": "Humidity",
      "dataKey": "value2",
      "addressType": "Coil",
      "address": "1102",
      "minValue": 0,
      "maxValue": 10000,
      "default_value": 0,
      "units": "%RH",
      "dataType": "Word",
      "multiplier": 0.01,
      "rw": "r"
    },
    {
      "name": "CO2",
      "dataKey": "value2",
      "addressType": "Coil",
      "address": "1103",
      "minValue": 400,
      "maxValue": 2000,
      "default_value": 0,
      "units": "ppm",
      "dataType": "Word",
      "multiplier": 1,
      "rw": "r"
    },
    {
      "name": "Particulates PM1",
      "dataKey": "value2",
      "addressType": "Coil",
      "address": "1104",
      "minValue": 0,
      "maxValue": 10000,
      "default_value": 0,
      "units": "ppm",
      "dataType": "Word",
      "multiplier": 0.01,
      "rw": "r"
    },
    {
      "name": "Particulates PM2.5",
      "dataKey": "value2",
      "addressType": "Coil",
      "address": "1105",
      "minValue": 0,
      "maxValue": 10000,
      "units": "ppm",
      "dataType": "Word",
      "multiplier": 0.01,
      "rw": "r"
    },
    {
      "name": "Particulates PM4",
      "dataKey": "value2",
      "addressType": "Coil",
      "address": "1106",
      "minValue": 0,
      "maxValue": 10000,
      "default_value": 0,
      "units": "pp",
      "dataType": "Word",
      "multiplier": 0.01,
      "rw": "r"
    },
    {
      "name": "Particulates PM10",
      "dataKey": "value2",
      "addressType": "Coil",
      "address": "1107",
      "minValue": 0,
      "maxValue": 10000,
      "default_value": 0,
      "units": "ppm",
      "dataType": "Word",
      "multiplier": 0.01,
      "rw": "r"
    },
    {
      "name": "Volatile Organic Compounds",
      "dataKey": "value2",
      "addressType": "Coil",
      "address": "1108",
      "minValue": 0,
      "maxValue": 10000,
      "default_value": 0,
      "units": "ppm",
      "dataType": "Word",
      "multiplier": 1,
      "rw": "r"
    },
    {
      "name": "Nitrous Oxide Gases",
      "dataKey": "value2",
      "addressType": "Coil",
      "address": "1109",
      "minValue": 0,
      "maxValue": 10000,
      "default_value": 0,
      "units": "ppm",
      "dataType": "Word",
      "multiplier": 1,
      "rw": "r"
    },
    {
      "name": "Differential Pressure",
      "dataKey": "value2",
      "addressType": "Coil",
      "address": "110a",
      "minValue": -5000,
      "maxValue": 5000,
      "default_value": 0,
      "units": "kPa",
      "dataType": "Word",
      "multiplier": 1,
      "rw": "r"
    },

    {
      "name": "Modbus Address",
      "dataKey": "value2",
      "addressType": "Register",
      "address": "2002",
      "minValue": 0,
      "maxValue": "FF",
      "default_value": 50,
      "units": "addr",
      "dataType": "Word",
      "multiplier": 1,
      "rw": "rw"
    },
    {
      "name": "BaudRate",
      "dataKey": "value2",
      "addressType": "Register",
      "address": "2003",
      "minValue": 0,
      "maxValue": 6,
      "default_value": 4,
      "units": "bps",
      "dataType": "Word",
      "multiplier": 1,
      "rw": "rw"
    }
  ]
}
